{
  "gmyw": "give me your wounded",
  "rr": "resounding rendition",
  "levin's": "levin's champion",
  "lc": "levin's champion",
  "heralds": "heralds of hinomoto",
  "hoh": "heralds of hinomoto",
  "choco": "the chocolatiers",
  "jots": "jewels of the sun",
  "vc": "valiant crown",
  "kfm": "kung fu masters",
  "ce": "crystalian envoy",
  "tso": "the shining overlord",
  "fitf": "flower in the fray",
  "bbw": "bonds between worlds",
  "fog": "flash of genius",
  "eol": "evening of luxury",
  "frh": "first-rate hospitality",
  "kc": "king's countenance"
}